griddle/__init__.py
griddle/py.typed
griddle-0.0.2.dist-info/METADATA
griddle-0.0.2.dist-info/WHEEL
griddle-0.0.2.dist-info/licenses/LICENSE.txt
griddle-0.0.2.dist-info/RECORD
