Metadata-Version: 2.1
Name: griddle
Version: 0.0.2
Summary: Turn an interable into a printable grid with dynamically controlled column sizes to shrink grid width to your terminal size.
Project-URL: Homepage, https://github.com/matt-manes/griddle
Project-URL: Documentation, https://github.com/matt-manes/griddle/tree/main/docs
Project-URL: Source code, https://github.com/matt-manes/griddle/tree/main/src/griddle
Author-email: Matt Manes <mattmanes@pm.me>
License-File: LICENSE.txt
Keywords: grid,print,tabulate,terminal
Classifier: License :: OSI Approved :: MIT License
Classifier: Operating System :: OS Independent
Classifier: Programming Language :: Python :: 3
Requires-Python: >=3.10
Requires-Dist: tabulate
